setup.py
smspdu/__init__.py
smspdu/smspdu.py
smspdu.egg-info/PKG-INFO
smspdu.egg-info/SOURCES.txt
smspdu.egg-info/dependency_links.txt
smspdu.egg-info/top_level.txt