Metadata-Version: 1.0
Name: smspdu
Version: 0.2
Summary: A module to decode SMS PDU format (and talk to an Ericcson T68 phone
Home-page: http://www.exothermia.net/monkeys_and_robots/2009/04/24/python-code-to-decode-sms-pdu/
Author: Eric Gradman
Author-email: eric@gradman.com
License: MIT
Platform: UNKNOWN
